byted_overpass_flow_qa_knowledge_base/__init__.py
byted_overpass_flow_qa_knowledge_base-0.0.1.dist-info/METADATA
byted_overpass_flow_qa_knowledge_base-0.0.1.dist-info/WHEEL
byted_overpass_flow_qa_knowledge_base-0.0.1.dist-info/top_level.txt
byted_overpass_flow_qa_knowledge_base-0.0.1.dist-info/RECORD
